hand_detection_v3/__init__.py
hand_detection_v3/hand_detection.py
hand_detection_v3-0.3.1.dist-info/LICENSE
hand_detection_v3-0.3.1.dist-info/METADATA
hand_detection_v3-0.3.1.dist-info/WHEEL
hand_detection_v3-0.3.1.dist-info/top_level.txt
hand_detection_v3-0.3.1.dist-info/RECORD
