Metadata-Version: 2.1
Name: hand-detection-v3
Version: 0.3.1
Summary: This is an installation package that detects the hand of the video.
Home-page: UNKNOWN
Author: llz
Author-email: hero1153@sina.com
License: MIT License
Platform: all
Classifier: Programming Language :: Python :: 3
Classifier: License :: OSI Approved :: MIT License
Classifier: Operating System :: OS Independent
